CS220_Lecture10_FSMCode/fsm_using_single_always.v
module fsm_using_single_always (
clock      , // clock
reset      , // Active high, syn reset
req_0      , // Request 0
req_1      , // Request 1
gnt_0      , // Grant 0
gnt_1
);

input   clock,reset,req_0,req_1;
output  gnt_0,gnt_1;
wire    clock,reset,req_0,req_1;
reg     gnt_0,gnt_1;
parameter SIZE = 3           ;
parameter IDLE  = 3'b001,GNT0 = 3'b010,GNT1 = 3'b100 ;
//=============Internal Variables======================
reg   [SIZE-1:0]          state        ;// Seq part of the FSM
reg   [SIZE-1:0]          next_state   ;// combo part of FSM
//==========Code startes Here==========================
always @ (posedge clock)
begin : FSM
if (reset == 1'b1) begin
  state <= #1 IDLE;
  gnt_0 <= 0;
  gnt_1 <= 0;
end else
 case(state)
   IDLE : begin if (req_0 == 1'b1) begin
                state <=  GNT0;
                //gnt_0 <= 1;
              end else if (req_1 == 1'b1) begin
                //gnt_1 <= 1;
                state <=  GNT1;
              end else begin
                state <=  IDLE;
              end
            gnt_0<=0;
            gnt_1<=0; end
   GNT0 : begin if (req_0 == 1'b1) begin
                state <=  GNT0;
                end
          else if(req_1==1'b1) begin
                state<= GNT1;
              end else begin

                state <= IDLE;
              end
              gnt_0 <= 1;
              gnt_1 <= 0;  end
   GNT1 : begin if (req_1 == 1'b1) begin
                state <=  GNT1;
                end
          else if(req_1==1'b1) begin
                state<= GNT0;
              end else begin
                state <=  IDLE;
              end
              gnt_0 <= 0;
              gnt_1 <= 1; end
   default : begin state <=  IDLE;
   gnt_0 <= 0;
   gnt_1 <= 0;
   end
endcase
end

endmodule

CS220_Lecture10_FSMCode/fsm_using_single_always_tb.v
`include "fsm_using_single_always.v"

module fsm_using_single_always_tb;
// Inputs
reg clock,reset,req_0,req_1;
wire [2:0] state;
// Outputs
wire gnt_0,gnt_1;

// Instantiate the Unit Under Test (UUT)
fsm_using_single_always m1(clock,reset,req_0,req_1,gnt_0,gnt_1);

always #1 clock=~clock;
initial
    begin
    $dumpfile("fsm_using_single_always.vcd");
    $dumpvars(0,fsm_using_single_always_tb);
        clock=1;
        #10;
        reset=1'b1;
        //state=3'b001;//idle
        req_0=1'b0;
        req_1=1'b0;
        #10;
        reset=1'b0;
        //state=3'b001;
        req_0=1'b1;
        req_1=1'b0;
        #10;
        reset=1'b0;
        //state=3'b010;
        req_0=1'b0;
        req_1=1'b0;
        #10;
        reset=1'b0;
        //state=3'b001;
        req_0=1'b0;
        req_1=1'b1;
        #10;
        reset=1'b0;
        //state=3'b100;
        req_0=1'b0;
        req_1=1'b0;
        #10;
        reset=1'b0;
        //state=3'b001;
        req_0=1'b1;
        req_1=1'b1;
        #10;

        $finish;
    end
endmodule

CS220_Lecture10_FSMCode/fsm_using_single_always.vcd
$date
	Fri Feb  3 01:12:07 2023
$end
$version
	Icarus Verilog
$end
$timescale
	1s
$end
$scope module fsm_using_single_always_tb $end
$var wire 1 ! gnt_1 $end
$var wire 1 " gnt_0 $end
$var reg 1 # clock $end
$var reg 1 $ req_0 $end
$var reg 1 % req_1 $end
$var reg 1 & reset $end
$scope module m1 $end
$var wire 1 # clock $end
$var wire 1 $ req_0 $end
$var wire 1 % req_1 $end
$var wire 1 & reset $end
$var reg 1 " gnt_0 $end
$var reg 1 ! gnt_1 $end
$var reg 3 ' state [2:0] $end
$scope begin FSM $end
$upscope $end
$upscope $end
$upscope $end
$enddefinitions $end
#0
$dumpvars
b1 '
x&
x%
x$
1#
0"
0!
$end
#1
0#
#2
1#
#3
0#
#4
1#
#5
0#
#6
1#
#7
0#
#8
1#
#9
0#
#10
1#
0%
0$
1&
#11
0#
#12
1#
#13
0#
#14
1#
#15
0#
#16
1#
#17
0#
#18
1#
#19
0#
#20
b10 '
1#
1$
0&
#21
0#
#22
1"
1#
#23
0#
#24
1#
#25
0#
#26
1#
#27
0#
#28
1#
#29
0#
#30
b1 '
1#
0$
#31
0#
#32
0"
1#
#33
0#
#34
1#
#35
0#
#36
1#
#37
0#
#38
1#
#39
0#
#40
b100 '
1#
1%
#41
0#
#42
1!
1#
#43
0#
#44
1#
#45
0#
#46
1#
#47
0#
#48
1#
#49
0#
#50
b1 '
1#
0%
#51
0#
#52
0!
1#
#53
0#
#54
1#
#55
0#
#56
1#
#57
0#
#58
1#
#59
0#
#60
b10 '
1#
1%
1$
#61
0#
#62
1"
1#
