week 1/4-bit ripple counter/D_FF.v
module D_FF(q, d, clk, reset);

input clk, reset, d;
output q;
reg q;

always @(posedge reset or negedge clk) begin
  if (reset)
    q <= 1'b0;
  else
    q <= d;
end

endmodule

week 1/4-bit ripple counter/T_FF.v
module T_FF(q, clk, reset);

output q;
input clk, reset;
wire d;

D_FF d_ff0(q, d, clk, reset);
not n1(d, q);

endmodule

week 1/4-bit ripple counter/ripple_carry_counter.v
module ripple_carry_counter(q, clk, reset);

input clk, reset;
output [3:0] q;

T_FF tff0(q[0], clk, reset);
T_FF tff1(q[1], q[0], reset);
T_FF tff2(q[2], q[1], reset);
T_FF tff3(q[3], q[2], reset);

endmodule

week 1/4-bit ripple counter/ripple_counter_tb.v
`timescale 1 ns/ 1ns

module ripple_counter_tb;

reg clk, reset;
wire [3:0] q;

ripple_carry_counter uut(.q(q), .clk(clk), .reset(reset));

initial begin
    clk <= 0;
    forever #10 clk <= ~clk;
end

initial begin

    $dumpfile("ripple_counter_tb.vcd");
    $dumpvars(0, ripple_counter_tb);

    reset = 1;
    #100 reset = 0;

    #2000 $finish;
end

endmodule

week 1/4-bit ripple counter/ripple_counter_tb.vcd
$date
	Thu Jan 12 15:07:52 2023
$end
$version
	Icarus Verilog
$end
$timescale
	1ns
$end
$scope module ripple_counter_tb $end
$var wire 4 ! q [3:0] $end
$var reg 1 " clk $end
$var reg 1 # reset $end
$scope module uut $end
$var wire 1 " clk $end
$var wire 1 # reset $end
$var wire 4 $ q [3:0] $end
$scope module tff0 $end
$var wire 1 " clk $end
$var wire 1 % d $end
$var wire 1 # reset $end
$var wire 1 & q $end
$scope module d_ff0 $end
$var wire 1 " clk $end
$var wire 1 % d $end
$var wire 1 # reset $end
$var reg 1 & q $end
$upscope $end
$upscope $end
$scope module tff1 $end
$var wire 1 ' clk $end
$var wire 1 ( d $end
$var wire 1 # reset $end
$var wire 1 ) q $end
$scope module d_ff0 $end
$var wire 1 ' clk $end
$var wire 1 ( d $end
$var wire 1 # reset $end
$var reg 1 ) q $end
$upscope $end
$upscope $end
$scope module tff2 $end
$var wire 1 * clk $end
$var wire 1 + d $end
$var wire 1 # reset $end
$var wire 1 , q $end
$scope module d_ff0 $end
$var wire 1 * clk $end
$var wire 1 + d $end
$var wire 1 # reset $end
$var reg 1 , q $end
$upscope $end
$upscope $end
$scope module tff3 $end
$var wire 1 - clk $end
$var wire 1 . d $end
$var wire 1 # reset $end
$var wire 1 / q $end
$scope module d_ff0 $end
$var wire 1 - clk $end
$var wire 1 . d $end
$var wire 1 # reset $end
$var reg 1 / q $end
$upscope $end
$upscope $end
$upscope $end
$upscope $end
$enddefinitions $end
#0
$dumpvars
0/
1.
0-
0,
1+
0*
0)
1(
0'
0&
1%
b0 $
1#
0"
b0 !
$end
#10
1"
#20
0"
#30
1"
#40
0"
#50
1"
#60
0"
#70
1"
#80
0"
#90
1"
#100
0%
1'
b1 !
b1 $
1&
0"
0#
#110
1"
#120
0(
1*
1)
1%
0'
b10 !
b10 $
0&
0"
#130
1"
#140
0%
1'
b11 !
b11 $
1&
0"
#150
1"
#160
0+
1-
1,
1(
0*
0)
1%
0'
b100 !
b100 $
0&
0"
#170
1"
#180
0%
1'
b101 !
b101 $
1&
0"
#190
1"
#200
0(
1*
1)
1%
0'
b110 !
b110 $
0&
0"
#210
1"
#220
0%
1'
b111 !
b111 $
1&
0"
#230
1"
#240
0.
1/
1+
0-
0,
1(
0*
0)
1%
0'
b1000 !
b1000 $
0&
0"
#250
1"
#260
0%
1'
b1001 !
b1001 $
1&
0"
#270
1"
#280
0(
1*
1)
1%
0'
b1010 !
b1010 $
0&
0"
#290
1"
#300
0%
1'
b1011 !
b1011 $
1&
0"
#310
1"
#320
0+
1-
1,
1(
0*
0)
1%
0'
b1100 !
b1100 $
0&
0"
#330
1"
#340
0%
1'
b1101 !
b1101 $
1&
0"
#350
1"
#360
0(
1*
1)
1%
0'
b1110 !
b1110 $
0&
0"
#370
1"
#380
0%
1'
b1111 !
b1111 $
1&
0"
#390
1"
#400
1.
0/
1+
0-
0,
1(
0*
0)
1%
0'
b0 !
b0 $
0&
0"
#410
1"
#420
0%
1'
b1 !
b1 $
1&
0"
#430
1"
#440
0(
1*
1)
1%
0'
b10 !
b10 $
0&
0"
#450
1"
#460
0%
1'
b11 !
b11 $
1&
0"
#470
1"
#480
0+
1-
1,
1(
0*
0)
1%
0'
b100 !
b100 $
0&
0"
#490
1"
#500
0%
1'
b101 !
b101 $
1&
0"
#510
1"
#520
0(
1*
1)
1%
0'
b110 !
b110 $
0&
0"
#530
1"
#540
0%
1'
b111 !
b111 $
1&
0"
#550
1"
#560
0.
1/
1+
0-
0,
1(
0*
0)
1%
0'
b1000 !
b1000 $
0&
0"
#570
1"
#580
0%
1'
b1001 !
b1001 $
1&
0"
#590
1"
#600
0(
1*
1)
1%
0'
b1010 !
b1010 $
0&
0"
#610
1"
#620
0%
1'
b1011 !
b1011 $
1&
0"
#630
1"
#640
0+
1-
1,
1(
0*
0)
1%
0'
b1100 !
b1100 $
0&
0"
#650
1"
#660
0%
1'
b1101 !
b1101 $
1&
0"
#670
1"
#680
0(
1*
1)
1%
0'
b1110 !
b1110 $
0&
0"
#690
1"
#700
0%
1'
b1111 !
b1111 $
1&
0"
#710
1"
#720
1.
0/
1+
0-
0,
1(
0*
0)
1%
0'
b0 !
b0 $
0&
0"
#730
1"
#740
0%
1'
b1 !
b1 $
1&
0"
#750
1"
#760
0(
1*
1)
1%
0'
b10 !
b10 $
0&
0"
#770
1"
#780
0%
1'
b11 !
b11 $
1&
0"
#790
1"
#800
0+
1-
1,
1(
0*
0)
1%
0'
b100 !
b100 $
0&
0"
#810
1"
#820
0%
1'
b101 !
b101 $
1&
0"
#830
1"
#840
0(
1*
1)
1%
0'
b110 !
b110 $
0&
0"
#850
1"
#860
0%
1'
b111 !
b111 $
1&
0"
#870
1"
#880
0.
1/
1+
0-
0,
1(
0*
0)
1%
0'
b1000 !
b1000 $
0&
0"
#890
1"
#900
0%
1'
b1001 !
b1001 $
1&
0"
#910
1"
#920
0(
1*
1)
1%
0'
b1010 !
b1010 $
0&
0"
#930
1"
#940
0%
1'
b1011 !
b1011 $
1&
0"
#950
1"
#960
0+
1-
1,
1(
0*
0)
1%
0'
b1100 !
b1100 $
0&
0"
#970
1"
#980
0%
1'
b1101 !
b1101 $
1&
0"
#990
1"
#1000
0(
1*
1)
1%
0'
b1110 !
b1110 $
0&
0"
#1010
1"
#1020
0%
1'
b1111 !
b1111 $
1&
0"
#1030
1"
#1040
1.
0/
1+
0-
0,
1(
0*
0)
1%
0'
b0 !
b0 $
0&
0"
#1050
1"
#1060
0%
1'
b1 !
b1 $
1&
0"
#1070
1"
#1080
0(
1*
1)
1%
0'
b10 !
b10 $
0&
0"
#1090
1"
#1100
0%
1'
b11 !
b11 $
1&
0"
#1110
1"
#1120
0+
1-
1,
1(
0*
0)
1%
0'
b100 !
b100 $
0&
0"
#1130
1"
#1140
0%
1'
b101 !
b101 $
1&
0"
#1150
1"
#1160
0(
1*
1)
1%
0'
b110 !
b110 $
0&
0"
#1170
1"
#1180
0%
1'
b111 !
b111 $
1&
0"
#1190
1"
#1200
0.
1/
1+
0-
0,
1(
0*
0)
1%
0'
b1000 !
b1000 $
0&
0"
#1210
1"
#1220
0%
1'
b1001 !
b1001 $
1&
0"
#1230
1"
#1240
0(
1*
1)
1%
0'
b1010 !
b1010 $
0&
0"
#1250
1"
#1260
0%
1'
b1011 !
b1011 $
1&
0"
#1270
1"
#1280
0+
1-
1,
1(
0*
0)
1%
0'
b1100 !
b1100 $
0&
0"
#1290
1"
#1300
0%
1'
b1101 !
b1101 $
1&
0"
#1310
1"
#1320
0(
1*
1)
1%
0'
b1110 !
b1110 $
0&
0"
#1330
1"
#1340
0%
1'
b1111 !
b1111 $
1&
0"
#1350
1"
#1360
1.
0/
1+
0-
0,
1(
0*
0)
1%
0'
b0 !
b0 $
0&
0"
#1370
1"
#1380
0%
1'
b1 !
b1 $
1&
0"
#1390
1"
#1400
0(
1*
1)
1%
0'
b10 !
b10 $
0&
0"
#1410
1"
#1420
0%
1'
b11 !
b11 $
1&
0"
#1430
1"
#1440
0+
1-
1,
1(
0*
0)
1%
0'
b100 !
b100 $
0&
0"
#1450
1"
#1460
0%
1'
b101 !
b101 $
1&
0"
#1470
1"
#1480
0(
1*
1)
1%
0'
b110 !
b110 $
0&
0"
#1490
1"
#1500
0%
1'
b111 !
b111 $
1&
0"
#1510
1"
#1520
0.
1/
1+
0-
0,
1(
0*
0)
1%
0'
b1000 !
b1000 $
0&
0"
#1530
1"
#1540
0%
1'
b1001 !
b1001 $
1&
0"
#1550
1"
#1560
0(
1*
1)
1%
0'
b1010 !
b1010 $
0&
0"
#1570
1"
#1580
0%
1'
b1011 !
b1011 $
1&
0"
#1590
1"
#1600
0+
1-
1,
1(
0*
0)
1%
0'
b1100 !
b1100 $
0&
0"
#1610
1"
#1620
0%
1'
b1101 !
b1101 $
1&
0"
#1630
1"
#1640
0(
1*
1)
1%
0'
b1110 !
b1110 $
0&
0"
#1650
1"
#1660
0%
1'
b1111 !
b1111 $
1&
0"
#1670
1"
#1680
1.
0/
1+
0-
0,
1(
0*
0)
1%
0'
b0 !
b0 $
0&
0"
#1690
1"
#1700
0%
1'
b1 !
b1 $
1&
0"
#1710
1"
#1720
0(
1*
1)
1%
0'
b10 !
b10 $
0&
0"
#1730
1"
#1740
0%
1'
b11 !
b11 $
1&
0"
#1750
1"
#1760
0+
1-
1,
1(
0*
0)
1%
0'
b100 !
b100 $
0&
0"
#1770
1"
#1780
0%
1'
b101 !
b101 $
1&
0"
#1790
1"
#1800
0(
1*
1)
1%
0'
b110 !
b110 $
0&
0"
#1810
1"
#1820
0%
1'
b111 !
b111 $
1&
0"
#1830
1"
#1840
0.
1/
1+
0-
0,
1(
0*
0)
1%
0'
b1000 !
b1000 $
0&
0"
#1850
1"
#1860
0%
1'
b1001 !
b1001 $
1&
0"
#1870
1"
#1880
0(
1*
1)
1%
0'
b1010 !
b1010 $
0&
0"
#1890
1"
#1900
0%
1'
b1011 !
b1011 $
1&
0"
#1910
1"
#1920
0+
1-
1,
1(
0*
0)
1%
0'
b1100 !
b1100 $
0&
0"
#1930
1"
#1940
0%
1'
b1101 !
b1101 $
1&
0"
#1950
1"
#1960
0(
1*
1)
1%
0'
b1110 !
b1110 $
0&
0"
#1970
1"
#1980
0%
1'
b1111 !
b1111 $
1&
0"
#1990
1"
#2000
1.
0/
1+
0-
0,
1(
0*
0)
1%
0'
b0 !
b0 $
0&
0"
#2010
1"
#2020
0%
1'
b1 !
b1 $
1&
0"
#2030
1"
#2040
0(
1*
1)
1%
0'
b10 !
b10 $
0&
0"
#2050
1"
#2060
0%
1'
b11 !
b11 $
1&
0"
#2070
1"
#2080
0+
1-
1,
1(
0*
0)
1%
0'
b100 !
b100 $
0&
0"
#2090
1"
#2100
0%
1'
b101 !
b101 $
1&
0"
