project/PC_control.v
module PC_control (
    PC_old, instruction, Jump, Branch, Bne, zero, PC_next
);

input [31:0] PC_old, instruction;
input Jump, Branch, Bne, zero;
output reg [31:0] PC_next;

reg [31:0] sign_ext;
reg [31:0] PC_old_temp;
reg [31:0] jump;
reg zero_temp;

initial begin
    PC_next = 32'b0;
end

always @ (PC_old) begin
    PC_old_temp = PC_old + 4;
end

always @ (zero, Bne) begin
    zero_temp = zero;
    if (Bne == 1) begin
        zero_temp = !zero_temp;
    end
end

always @ (instruction) begin
    jump = {4'b0, instruction[25:0], 2'b0};
    // sign extension
    if (instruction[15] == 1'b0) begin
        sign_ext = {16'b0, instruction[15:0]};
    end
    else begin
        sign_ext = {{16{1'b1}}, instruction[15:0]};
    end
    sign_ext = {sign_ext[29:0], 2'b0};
end

always @ (instruction or PC_old_temp or jump) begin
    jump = {PC_old_temp[31:26], jump[27:0]};
end

always @ (PC_old_temp, sign_ext, jump, Branch, zero_temp, Jump) begin
    if (Branch == 1 & zero_temp == 1) begin
        PC_next = PC_old_temp + sign_ext;
    end
    else begin
        PC_next = PC_old_temp;
    end
    if (Jump == 1) begin
        PC_next = jump;
    end
end

endmodule

project/dataMemory.v
module dataMemory(
    clk, address, writeData, ALUResult, MemWrite, MemRead, MemtoReg, readData
);

input clk;
input [31:0] address, writeData, ALUResult;
input MemWrite, MemRead, MemtoReg;
output reg [31:0] readData;

parameter DATA_MEM_SIZE = 128;
reg [31:0] dataMemory[DATA_MEM_SIZE-1:0];

integer i;
initial begin
    for (i = 0; i < DATA_MEM_SIZE; i = i + 1) begin
        dataMemory[i] = 32'b0;
    end
end

// reading from memory

always @(address or MemRead or MemtoReg or ALUResult) begin
    if (MemRead == 1) begin
        if (MemtoReg == 1) begin
            readData = dataMemory[address];
        end else begin
            readData = ALUResult;
        end
    end else begin
        readData = ALUResult;
    end
end

// writing to memory

always @(posedge clk) begin
    if (MemWrite == 1) begin
        dataMemory[address] = writeData;
    end
end

endmodule

project/Control_unit.v
module Control_Unit(
    instruction,
    RegDst,
    Jump,
    Branch,
    Bne,
    MemRead,
    MemtoReg,
    ALUOp,
    MemWrite,
    ALUSrc,
    RegWrite
);

input [31:0] instruction;
output reg RegDst, Jump, Branch, Bne, MemRead, MemtoReg, MemWrite, ALUSrc, RegWrite;
output reg [1:0] ALUOp;

initial begin
    RegDst = 0;
    Jump = 0;
    Branch = 0;
    Bne = 0;
    MemRead = 0;
    MemtoReg = 0;
    ALUOp = 2'b00;
    MemWrite = 0;
    ALUSrc = 0;
    RegWrite = 0;
end

always @ (instruction) begin
    case (instruction[31:26])   // checking the opcode
        6'b000000: begin    // arithmetic (add and sub)
            RegDst = 1;
            ALUSrc = 0;
            MemtoReg = 0;
            RegWrite = 1;
            MemRead = 0;
            MemWrite = 0;
            Branch = 0;
            Bne = 0;
            ALUOp = 2'b10;
            Jump = 0;
        end
        6'b001000: begin    // addi
            RegDst = 0;
            ALUSrc = 1;
            MemtoReg = 0;
            RegWrite = 1;
            MemRead = 0;
            MemWrite = 0;
            Branch = 0;
            Bne = 0;
            ALUOp = 2'b00;
            Jump = 0;
        end
        6'b001100: begin  // andi
        RegDst = 0;
        ALUSrc = 1;
        MemtoReg = 0;
        RegWrite = 1;
        MemRead = 0;
        MemWrite = 0;
        Branch = 0;
        Bne = 0;
        ALUOp = 2'b11;
        Jump = 0;
      end
      6'b100011: begin  // lw
        RegDst = 0;
        ALUSrc = 1;
        MemtoReg = 1;
        RegWrite = 1;
        MemRead = 1;
        MemWrite = 0;
        Branch = 0;
        Bne = 0;
        ALUOp = 2'b00;
        Jump = 0;
      end
      6'b101011: begin  // sw
        RegDst = 0;
        ALUSrc = 1;
        MemtoReg = 0;
        RegWrite = 0;
        MemRead = 0;
        MemWrite = 1;
        Branch = 0;
        Bne = 0;
        ALUOp = 2'b00;
        Jump = 0;
      end
      6'b000100: begin  // beq
        RegDst = 0;
        ALUSrc = 0;
        MemtoReg = 0;
        RegWrite = 0;
        MemRead = 0;
        MemWrite = 0;
        Branch = 1;
        Bne = 0;
        ALUOp = 2'b01;
        Jump = 0;
      end
      6'b000101: begin  // bne
        RegDst = 0;
        ALUSrc = 0;
        MemtoReg = 0;
        RegWrite = 0;
        MemRead = 0;
        MemWrite = 0;
        Branch = 1;
        Bne = 1;
        ALUOp = 2'b01;
        Jump = 0;
      end
      6'b000010: begin  // j
        RegDst = 0;
        ALUSrc = 0;
        MemtoReg = 0;
        RegWrite = 0;
        MemRead = 0;
        MemWrite = 0;
        Branch = 0;
        Bne = 0;
        ALUOp = 2'b01;
        Jump = 1;
      end
      default: begin
        RegDst = 0;
        ALUSrc = 0;
        MemtoReg = 0;
        RegWrite = 0;
        MemRead = 0;
        MemWrite = 0;
        Branch = 0;
        Bne = 0;
        ALUOp = 2'b00;
        Jump = 0;
      end
    endcase 
end

endmodule

project/ALUControlUnit.v
module ALU_control(ALUCnt, ALUOp, funcode);

input [1:0] ALUOp;
input [5:0] funcode;
output reg [3:0] ALUCnt;

always @ (ALUOp, funcode) begin
    if (ALUOp == 2'b00) begin
        ALUCnt = 4'b0010;   // add and lw/sw
    end 
    else if (ALUOp == 2'b01) begin
        ALUCnt = 4'b0110;   // sub and beq
    end
    else if (ALUOp == 2'b10) begin  // R-Type
        case (funcode)
            6'b100000:  // add
                ALUCnt = 4'b0010;
            6'b100010:  // sub
                ALUCnt = 4'b0110;
            6'b100100:  // and
                ALUCnt = 4'b0000;
            6'b100101:  // or
                ALUCnt = 4'b0001;
            6'b101010:  // slt
                ALUCnt = 4'b0111;
            default:
                ALUCnt = 4'b0000;
        endcase
    end
    else if (ALUOp == 2'b11) begin  // NOR
        ALUCnt = 4'b0000;
    end
    else begin
        ALUCnt = 4'b0000;
    end
end


endmodule

project/MIPS_ALU.v
module ALU (
    data1,        // data 1
    read2,        // data 2 from MUX
    instruction,  // used for sign-extension
    ALUSrc,
    ALUCnt,
    zero,
    ALUResult
);

input [31:0] data1, read2, instruction;
input ALUSrc;
input [3:0] ALUCnt;
output reg zero;
output reg [31:0] ALUResult;

reg [31:0] data2;

// deciding inputs to ALU

always @ (ALUSrc, read2, instruction) begin
    if (ALUSrc == 0) begin
        data2 = read2;
    end else begin
        if (instruction[15] == 0) begin
            data2 = {16'b0, instruction[15:0]};
        end else begin
            data2 = {{16{1'b1}}, instruction[15:0]};
        end
        // simple sign extension
    end
end

always @ (data1, data2, ALUCnt) begin
    case (ALUCnt)
        4'b0000:
            ALUResult = data1 & data2;  // AND
        4'b0001:
            ALUResult = data1 | data2;  // OR
        4'b0010:
            ALUResult = data1 + data2;  // ADD
        4'b0110:
            ALUResult = data1 - data2;  // SUB
        4'b0111:
            ALUResult = (data1 < data2) ? 1 : 0;  // SLT
        4'b1100:
            ALUResult = data1 | ~data2;  // NOR
        default:
            ALUResult = 0;
    endcase
    // assigning zero
    zero = (ALUResult == 0) ? 1 : 0;
end


endmodule

project/Veda.v
module Veda (
    input clk,
    input [31:0] instruction,  // the raw 32-bit instruction
    input RegWrite,
    input RegDst,
    input [31:0] WriteData,  // from WB stage
    output [31:0] ReadData1,
    output [31:0] ReadData2
);

  reg [31:0] RegData[31:0];  // register data

  // initialize the regester data
  integer i;
  initial begin
    for (i = 0; i < 32; i = i + 1) begin
      RegData[i] = 32'b0;
    end
  end

  assign ReadData1 = RegData[instruction[25:21]];
  assign ReadData2 = RegData[instruction[20:16]];

  always @(posedge clk) begin  // RegWrite, RegDst, WriteData, instruction)
    if (RegWrite == 1'b1) begin
      // $display("Reg_WriteData: 0x%H",WriteData);
      if (RegDst == 1'b0) begin
        RegData[instruction[20:16]] = WriteData;
      end else begin
        RegData[instruction[15:11]] = WriteData;
      end
    end
  end

endmodule

project/instructionRegister.v
module instructionRegister(
    address, opcode, funcode, instruction
);

input [31:0] address;
output reg [5:0] opcode, funcode;
output reg [31:0] instruction;

parameter INSTRUCTION_MEM_SIZE = 128;
reg [31:0] instructionMemory[INSTRUCTION_MEM_SIZE-1:0];

integer i;
initial begin
    for (i = 0; i < INSTRUCTION_MEM_SIZE; i = i + 1) begin
        instructionMemory[i] = 32'b11111100000000000000000000000000;
    end
    $readmemb("instructions_storage.mem", instructionMemory);

    instruction = 32'b11111100000000000000000000000000;
end

always @ (address) begin
    if (address == -4) begin  // init
        instruction = 32'b11111100000000000000000000000000;
    end else begin
        instruction = instructionMemory[address>>2];
    end
    opcode = instruction[31:26];
    funcode = instruction[5:0];
end

endmodule

project/PC.v
module Program_counter (
    clk,
    PC_next,
    PC_out
);

input clk;
input [31:0] PC_next;
output reg [31:0] PC_out;

initial begin
    PC_out = -4;   // preventing default
end

always @ (posedge clk) begin
    PC_out = PC_next;
end

endmodule

project/datapath.v
module datapath (clk);

input clk;

wire [31:0] pc_in, pc_out;
wire [5:0] opcode;
wire [5:0] funcode;
wire [31:0] instruction, read_wbdata, read_data1, read_data2;
wire RegDst, Jump, Branch, Bne, MemRead, MemtoReg, MemWrite, ALUSrc, RegWrite;
wire [1:0] ALUOp;
wire [3:0] ALUCnt;
wire zero;
wire [31:0] ALUResult;

Program_counter uPC (
    .clk(clk),
    .PC_next(pc_in),
    .PC_out(pc_out)
);

instructionRegister uIR (
    .address(pc_out),
    .opcode(opcode),
    .funcode(funcode),
    .instruction(instruction)
);

Veda uVeda (
    .clk(clk),
    .instruction(instruction),
    .RegWrite(RegWrite),
    .RegDst(RegDst),
    .WriteData(read_wbdata),
    .ReadData1(read_data1),
    .ReadData2(read_data2)
);

ALU uALU (
    .data1(read_data1),
    .read2(read_data2),
    .instruction(instruction),
    .ALUSrc(ALUSrc),
    .ALUCnt(ALUCnt),
    .zero(zero),
    .ALUResult(ALUResult)
);

ALU_control uALU_control (
    .ALUOp(ALUOp),
    .funcode(funcode),
    .ALUCnt(ALUCnt)
);

Control_Unit uControl(
    .instruction(instruction),
    .RegDst(RegDst),
    .Jump(Jump),
    .Branch(Branch),
    .Bne(Bne),
    .MemRead(MemRead),
    .MemtoReg(MemtoReg),
    .ALUOp(ALUOp),
    .MemWrite(MemWrite),
    .ALUSrc(ALUSrc),
    .RegWrite(RegWrite)
);

dataMemory uDataMemory (
    .clk(clk),
    .address(ALUResult),
    .writeData(read_data2),
    .ALUResult(ALUResult),
    .MemWrite(MemWrite),
    .MemRead(MemRead),
    .MemtoReg(MemtoReg),
    .readData(read_wbdata)
);

PC_control uPC_control (
    .PC_old(pc_out),
    .instruction(instruction),
    .Jump(Jump),
    .Branch(Branch),
    .Bne(Bne),
    .zero(zero),
    .PC_next(pc_in)
);

endmodule

project/tb.v
`define CYCLE_TIME 40

module tb;

  reg clk;
  integer i; // integer  counter

  always #(`CYCLE_TIME / 2) clk = ~clk;

  datapath uut (.clk(clk));

  initial begin
    // Initialize data memory
    for (i = 9; i < 32; i = i + 1) begin
      uut.uDataMemory.dataMemory[i] = 32'b0;
    end
      uut.uDataMemory.dataMemory[0] = 11;
      uut.uDataMemory.dataMemory[1] = 13;
      uut.uDataMemory.dataMemory[2] = 255;
      uut.uDataMemory.dataMemory[3] = 10;
      uut.uDataMemory.dataMemory[4] = 69;
      uut.uDataMemory.dataMemory[5] = 24;
      uut.uDataMemory.dataMemory[6] = 48;
      uut.uDataMemory.dataMemory[7] = 802;
      uut.uDataMemory.dataMemory[8] = 10;

    $dumpfile("tb.vcd");
    $dumpvars(0, tb);

    clk = 0;
  end

  always @(posedge clk) begin

    $display("_________________________________________________________________________________________________________");
    $display($time,, "PC: %d \n Data_memory:= %d %d %d %d %d %d %d %d %d ", uut.uPC.PC_out, 
             uut.uDataMemory.dataMemory[0], uut.uDataMemory.dataMemory[1], uut.uDataMemory.dataMemory[2], uut.uDataMemory.dataMemory[3],uut.uDataMemory.dataMemory[4], uut.uDataMemory.dataMemory[5], uut.uDataMemory.dataMemory[6], uut.uDataMemory.dataMemory[7], uut.
             uDataMemory.dataMemory[8]);
    $display("_________________________________________________________________________________________________________");
  end

  
  initial begin
    #10000 $finish;
  end


endmodule

project/tb.vcd
$date
	Sun Apr 16 15:34:10 2023
$end
$version
	Icarus Verilog
$end
$timescale
	1ps
$end
$scope module tb $end
$var reg 1 ! clk $end
$var integer 32 " i [31:0] $end
$scope module uut $end
$var wire 1 ! clk $end
$var wire 1 # zero $end
$var wire 32 $ read_wbdata [31:0] $end
$var wire 32 % read_data2 [31:0] $end
$var wire 32 & read_data1 [31:0] $end
$var wire 32 ' pc_out [31:0] $end
$var wire 32 ( pc_in [31:0] $end
$var wire 6 ) opcode [5:0] $end
$var wire 32 * instruction [31:0] $end
$var wire 6 + funcode [5:0] $end
$var wire 1 , RegWrite $end
$var wire 1 - RegDst $end
$var wire 1 . MemtoReg $end
$var wire 1 / MemWrite $end
$var wire 1 0 MemRead $end
$var wire 1 1 Jump $end
$var wire 1 2 Branch $end
$var wire 1 3 Bne $end
$var wire 1 4 ALUSrc $end
$var wire 32 5 ALUResult [31:0] $end
$var wire 2 6 ALUOp [1:0] $end
$var wire 4 7 ALUCnt [3:0] $end
$scope module uALU $end
$var wire 32 8 read2 [31:0] $end
$var wire 32 9 instruction [31:0] $end
$var wire 32 : data1 [31:0] $end
$var wire 1 4 ALUSrc $end
$var wire 4 ; ALUCnt [3:0] $end
$var reg 32 < ALUResult [31:0] $end
$var reg 32 = data2 [31:0] $end
$var reg 1 # zero $end
$upscope $end
$scope module uALU_control $end
$var wire 6 > funcode [5:0] $end
$var wire 2 ? ALUOp [1:0] $end
$var reg 4 @ ALUCnt [3:0] $end
$upscope $end
$scope module uControl $end
$var wire 32 A instruction [31:0] $end
$var reg 2 B ALUOp [1:0] $end
$var reg 1 4 ALUSrc $end
$var reg 1 3 Bne $end
$var reg 1 2 Branch $end
$var reg 1 1 Jump $end
$var reg 1 0 MemRead $end
$var reg 1 / MemWrite $end
$var reg 1 . MemtoReg $end
$var reg 1 - RegDst $end
$var reg 1 , RegWrite $end
$upscope $end
$scope module uDataMemory $end
$var wire 32 C ALUResult [31:0] $end
$var wire 1 0 MemRead $end
$var wire 1 / MemWrite $end
$var wire 1 . MemtoReg $end
$var wire 32 D address [31:0] $end
$var wire 1 ! clk $end
$var wire 32 E writeData [31:0] $end
$var reg 32 F readData [31:0] $end
$var integer 32 G i [31:0] $end
$upscope $end
$scope module uIR $end
$var wire 32 H address [31:0] $end
$var reg 6 I funcode [5:0] $end
$var reg 32 J instruction [31:0] $end
$var reg 6 K opcode [5:0] $end
$var integer 32 L i [31:0] $end
$upscope $end
$scope module uPC $end
$var wire 1 ! clk $end
$var wire 32 M PC_next [31:0] $end
$var reg 32 N PC_out [31:0] $end
$upscope $end
$scope module uPC_control $end
$var wire 1 3 Bne $end
$var wire 1 2 Branch $end
$var wire 1 1 Jump $end
$var wire 32 O PC_old [31:0] $end
$var wire 32 P instruction [31:0] $end
$var wire 1 # zero $end
$var reg 32 Q PC_next [31:0] $end
$var reg 32 R PC_old_temp [31:0] $end
$var reg 32 S jump [31:0] $end
$var reg 32 T sign_ext [31:0] $end
$var reg 1 U zero_temp $end
$upscope $end
$scope module uVeda $end
$var wire 32 V ReadData1 [31:0] $end
$var wire 32 W ReadData2 [31:0] $end
$var wire 1 - RegDst $end
$var wire 1 , RegWrite $end
$var wire 32 X WriteData [31:0] $end
$var wire 1 ! clk $end
$var wire 32 Y instruction [31:0] $end
$var integer 32 Z i [31:0] $end
$upscope $end
$upscope $end
$upscope $end
$enddefinitions $end
#0
$dumpvars
b100000 Z
b11111100000000000000000000000000 Y
b0 X
b0 W
b0 V
1U
b0 T
b0 S
b0 R
b0 Q
b11111100000000000000000000000000 P
b11111111111111111111111111111100 O
b11111111111111111111111111111100 N
b0 M
b10000000 L
b111111 K
b11111100000000000000000000000000 J
b0 I
b11111111111111111111111111111100 H
b10000000 G
b0 F
b0 E
b0 D
b0 C
b0 B
b11111100000000000000000000000000 A
b10 @
b0 ?
b0 >
b0 =
b0 <
b10 ;
b0 :
b11111100000000000000000000000000 9
b0 8
b10 7
b0 6
b0 5
04
03
02
01
00
0/
0.
0-
0,
b0 +
b11111100000000000000000000000000 *
b111111 )
b0 (
b11111111111111111111111111111100 '
b0 &
b0 %
b0 $
1#
b100000 "
0!
$end
#20000
0U
b1001 $
b1001 F
b1001 X
0#
b1001 5
b1001 <
b1001 C
b1001 D
b1001 =
1,
14
b100100 T
b1000110001000000000000100100 S
b100 (
b100 M
b100 Q
b1001 +
b1001 >
b1001 I
b1000 )
b1000 K
b100010001100010000000000001001 *
b100010001100010000000000001001 9
b100010001100010000000000001001 A
b100010001100010000000000001001 J
b100010001100010000000000001001 P
b100010001100010000000000001001 Y
b100 R
b0 '
b0 H
b0 N
b0 O
1!
#40000
0!
#60000
b1000 $
b1000 F
b1000 X
b1000 (
b1000 M
b1000 Q
b11111111111111111111111111111100 T
b1000110001111111111111111100 S
b1000 5
b1000 <
b1000 C
b1000 D
b11111111111111111111111111111111 =
b1000 R
b111111 +
b111111 >
b111111 I
b100010001100011111111111111111 *
b100010001100011111111111111111 9
b100010001100011111111111111111 A
b100010001100011111111111111111 J
b100010001100011111111111111111 P
b100010001100011111111111111111 Y
b1001 &
b1001 :
b1001 V
b1001 %
b1001 8
b1001 E
b1001 W
b100 '
b100 H
b100 N
b100 O
1!
#80000
0!
#100000
1U
1#
b0 =
b0 T
b1001000000000000000000 S
b1100 (
b1100 M
b1100 Q
b0 $
b0 F
b0 X
b0 +
b0 >
b0 I
b100000000010010000000000000000 *
b100000000010010000000000000000 9
b100000000010010000000000000000 A
b100000000010010000000000000000 J
b100000000010010000000000000000 P
b100000000010010000000000000000 Y
b1100 R
b0 5
b0 <
b0 C
b0 D
b1000 '
b1000 H
b1000 N
b1000 O
b0 &
b0 :
b0 V
b0 %
b0 8
b0 E
b0 W
1!
#120000
0!
#140000
b10000 (
b10000 M
b10000 Q
b1010000000000000000000 S
b10000 R
b100000000010100000000000000000 *
b100000000010100000000000000000 9
b100000000010100000000000000000 A
b100000000010100000000000000000 J
b100000000010100000000000000000 P
b100000000010100000000000000000 Y
b1100 '
b1100 H
b1100 N
b1100 O
1!
#160000
0!
#180000
0U
b1000 $
b1000 F
b1000 X
0#
b1000 5
b1000 <
b1000 C
b1000 D
b110 7
b110 ;
b110 @
b1000 &
b1000 :
b1000 V
b10 6
b10 ?
b10 B
04
1-
b11111111111111101110000010001000 T
b1000101001101110000010001000 S
b10100 (
b10100 M
b10100 Q
b100010 +
b100010 >
b100010 I
b0 )
b0 K
b10001010011011100000100010 *
b10001010011011100000100010 9
b10001010011011100000100010 A
b10001010011011100000100010 J
b10001010011011100000100010 P
b10001010011011100000100010 Y
b10100 R
b10000 '
b10000 H
b10000 N
b10000 O
1!
#200000
0!
#220000
1U
b0 $
b0 F
b0 X
1#
b0 5
b0 <
b0 C
b0 D
b11000 (
b11000 M
b11000 Q
b10 7
b10 ;
b10 @
b0 &
b0 :
b0 V
b0 T
b1000010010000000000000000000 S
b0 6
b0 ?
b0 B
14
0-
b11000 R
b0 +
b0 >
b0 I
b1000 )
b1000 K
b100010000100100000000000000000 *
b100010000100100000000000000000 9
b100010000100100000000000000000 A
b100010000100100000000000000000 J
b100010000100100000000000000000 P
b100010000100100000000000000000 Y
b10100 '
b10100 H
b10100 N
b10100 O
1!
#240000
0!
#260000
b1011 $
b1011 F
b1011 X
10
1.
b1001001011000000000000000000 S
b11100 (
b11100 M
b11100 Q
b100011 )
b100011 K
b10001110010010110000000000000000 *
b10001110010010110000000000000000 9
b10001110010010110000000000000000 A
b10001110010010110000000000000000 J
b10001110010010110000000000000000 P
b10001110010010110000000000000000 Y
b11100 R
b11000 '
b11000 H
b11000 N
b11000 O
1!
#280000
0!
#300000
0U
b1101 $
b1101 F
b1101 X
0#
b1 5
b1 <
b1 C
b1 D
b100000 (
b100000 M
b100000 Q
b100 T
b1001001100000000000000000100 S
b1 =
b100000 R
b1 +
b1 >
b1 I
b10001110010011000000000000000001 *
b10001110010011000000000000000001 9
b10001110010011000000000000000001 A
b10001110010011000000000000000001 J
b10001110010011000000000000000001 P
b10001110010011000000000000000001 Y
b0 %
b0 8
b0 E
b0 W
b11100 '
b11100 H
b11100 N
b11100 O
1!
#320000
0!
#340000
1U
1#
b0 5
b0 <
b0 C
b0 D
b0 $
b0 F
b0 X
b111 7
b111 ;
b111 @
b1101 &
b1101 :
b1101 V
b1011 =
b10 6
b10 ?
b10 B
00
0.
04
1-
b11111111111111110000000010101000 T
b110001011110000000010101000 S
b100100 (
b100100 M
b100100 Q
b101010 +
b101010 >
b101010 I
b0 )
b0 K
b1100010111100000000101010 *
b1100010111100000000101010 9
b1100010111100000000101010 A
b1100010111100000000101010 J
b1100010111100000000101010 P
b1100010111100000000101010 Y
b100100 R
b100000 '
b100000 H
b100000 N
b100000 O
b1011 %
b1011 8
b1011 E
b1011 W
1!
#360000
0!
#380000
b0 =
b110000 (
b110000 M
b110000 Q
b110 7
b110 ;
b110 @
b0 &
b0 :
b0 V
b0 %
b0 8
b0 E
b0 W
b1000 T
b1100000000000000000000001000 S
b1 6
b1 ?
b1 B
12
0,
0-
b101000 R
b10 +
b10 >
b10 I
b100 )
b100 K
b10011000000000000000000000010 *
b10011000000000000000000000010 9
b10011000000000000000000000010 A
b10011000000000000000000000010 J
b10011000000000000000000000010 P
b10011000000000000000000000010 Y
b100100 '
b100100 H
b100100 N
b100100 O
1!
#400000
0!
#420000
0U
b1 $
b1 F
b1 X
0#
b1 5
b1 <
b1 C
b1 D
b10 7
b10 ;
b10 @
b1 =
b0 6
b0 ?
b0 B
02
1,
14
b100 T
b1001010010000000000000000100 S
b110100 (
b110100 M
b110100 Q
b1 +
b1 >
b1 I
b1000 )
b1000 K
b100010010100100000000000000001 *
b100010010100100000000000000001 9
b100010010100100000000000000001 A
b100010010100100000000000000001 J
b100010010100100000000000000001 P
b100010010100100000000000000001 Y
b110100 R
b110000 '
b110000 H
b110000 N
b110000 O
1!
#440000
0!
#460000
b1 $
b1 F
b1 X
b111000 (
b111000 M
b111000 Q
b100 T
b101001010000000000000000100 S
b1 5
b1 <
b1 C
b1 D
b111000 R
b100001010010100000000000000001 *
b100001010010100000000000000001 9
b100001010010100000000000000001 A
b100001010010100000000000000001 J
b100001010010100000000000000001 P
b100001010010100000000000000001 Y
b0 &
b0 :
b0 V
b0 %
b0 8
b0 E
b0 W
b110100 '
b110100 H
b110100 N
b110100 O
1!
#480000
0!
#500000
b1000 =
1U
b110 7
b110 ;
b110 @
b1 6
b1 ?
b1 B
13
12
0,
04
b11111111111111111111111111011100 T
b101010111111111111111011100 S
b11000 (
b11000 M
b11000 Q
b11111111111111111111111111111001 $
b11111111111111111111111111111001 F
b11111111111111111111111111111001 X
b110111 +
b110111 >
b110111 I
b101 )
b101 K
b10101010101111111111111110111 *
b10101010101111111111111110111 9
b10101010101111111111111110111 A
b10101010101111111111111110111 J
b10101010101111111111111110111 P
b10101010101111111111111110111 Y
b111100 R
b11111111111111111111111111111001 5
b11111111111111111111111111111001 <
b11111111111111111111111111111001 C
b11111111111111111111111111111001 D
b111000 '
b111000 H
b111000 N
b111000 O
b1 &
b1 :
b1 V
b1000 %
b1000 8
b1000 E
b1000 W
1!
#520000
0!
#540000
b1 5
b1 <
b1 C
b1 D
0U
b1101 $
b1101 F
b1101 X
b11100 (
b11100 M
b11100 Q
b10 7
b10 ;
b10 @
b1011 %
b1011 8
b1011 E
b1011 W
b0 =
b0 T
b1001001011000000000000000000 S
b0 6
b0 ?
b0 B
03
02
10
1,
1.
14
b11100 R
b0 +
b0 >
b0 I
b100011 )
b100011 K
b10001110010010110000000000000000 *
b10001110010010110000000000000000 9
b10001110010010110000000000000000 A
b10001110010010110000000000000000 J
b10001110010010110000000000000000 P
b10001110010010110000000000000000 Y
b11000 '
b11000 H
b11000 N
b11000 O
1!
#560000
0!
#580000
b11111111 $
b11111111 F
b11111111 X
b10 5
b10 <
b10 C
b10 D
b1 =
b100 T
b1001001100000000000000000100 S
b100000 (
b100000 M
b100000 Q
b1 +
b1 >
b1 I
b10001110010011000000000000000001 *
b10001110010011000000000000000001 9
b10001110010011000000000000000001 A
b10001110010011000000000000000001 J
b10001110010011000000000000000001 P
b10001110010011000000000000000001 Y
b100000 R
b11100 '
b11100 H
b11100 N
b11100 O
b1101 %
b1101 8
b1101 E
b1101 W
1!
#600000
0!
#620000
1U
1#
b0 $
b0 F
b0 X
b0 5
b0 <
b0 C
b0 D
b100100 (
b100100 M
b100100 Q
b111 7
b111 ;
b111 @
b11111111 &
b11111111 :
b11111111 V
b11111111111111110000000010101000 T
b110001011110000000010101000 S
b10 6
b10 ?
b10 B
00
0.
04
1-
b1101 =
b100100 R
b101010 +
b101010 >
b101010 I
b0 )
b0 K
b1100010111100000000101010 *
b1100010111100000000101010 9
b1100010111100000000101010 A
b1100010111100000000101010 J
b1100010111100000000101010 P
b1100010111100000000101010 Y
b1101 %
b1101 8
b1101 E
b1101 W
b100000 '
b100000 H
b100000 N
b100000 O
1!
#640000
0!
#660000
b0 =
b110 7
b110 ;
b110 @
b0 &
b0 :
b0 V
b0 %
b0 8
b0 E
b0 W
b1 6
b1 ?
b1 B
12
0,
0-
b1000 T
b1100000000000000000000001000 S
b110000 (
b110000 M
b110000 Q
b10 +
b10 >
b10 I
b100 )
b100 K
b10011000000000000000000000010 *
b10011000000000000000000000010 9
b10011000000000000000000000010 A
b10011000000000000000000000010 J
b10011000000000000000000000010 P
b10011000000000000000000000010 Y
b101000 R
b100100 '
b100100 H
b100100 N
b100100 O
1!
#680000
0!
#700000
0U
b10 $
b10 F
b10 X
0#
b10 5
b10 <
b10 C
b10 D
b110100 (
b110100 M
b110100 Q
b10 7
b10 ;
b10 @
b1 &
b1 :
b1 V
b1 %
b1 8
b1 E
b1 W
b1 =
b100 T
b1001010010000000000000000100 S
b0 6
b0 ?
b0 B
02
1,
14
b110100 R
b1 +
b1 >
b1 I
b1000 )
b1000 K
b100010010100100000000000000001 *
b100010010100100000000000000001 9
b100010010100100000000000000001 A
b100010010100100000000000000001 J
b100010010100100000000000000001 P
b100010010100100000000000000001 Y
b110000 '
b110000 H
b110000 N
b110000 O
1!
#720000
0!
#740000
b100 T
b101001010000000000000000100 S
b111000 (
b111000 M
b111000 Q
b10 $
b10 F
b10 X
b100001010010100000000000000001 *
b100001010010100000000000000001 9
b100001010010100000000000000001 A
b100001010010100000000000000001 J
b100001010010100000000000000001 P
b100001010010100000000000000001 Y
b111000 R
b10 5
b10 <
b10 C
b10 D
b110100 '
b110100 H
b110100 N
b110100 O
b1 &
b1 :
b1 V
b1 %
b1 8
b1 E
b1 W
1!
#760000
0!
#780000
1U
b11111111111111111111111111111010 $
b11111111111111111111111111111010 F
b11111111111111111111111111111010 X
b11000 (
b11000 M
b11000 Q
b110 7
b110 ;
b110 @
b11111111111111111111111111011100 T
b101010111111111111111011100 S
b1 6
b1 ?
b1 B
13
12
0,
04
b11111111111111111111111111111010 5
b11111111111111111111111111111010 <
b11111111111111111111111111111010 C
b11111111111111111111111111111010 D
b1000 =
b111100 R
b110111 +
b110111 >
b110111 I
b101 )
b101 K
b10101010101111111111111110111 *
b10101010101111111111111110111 9
b10101010101111111111111110111 A
b10101010101111111111111110111 J
b10101010101111111111111110111 P
b10101010101111111111111110111 Y
b10 &
b10 :
b10 V
b1000 %
b1000 8
b1000 E
b1000 W
b111000 '
b111000 H
b111000 N
b111000 O
1!
#800000
0!
#820000
b10 5
b10 <
b10 C
b10 D
0U
b11111111 $
b11111111 F
b11111111 X
b10 7
b10 ;
b10 @
b1101 %
b1101 8
b1101 E
b1101 W
b0 =
b0 6
b0 ?
b0 B
03
02
10
1,
1.
14
b0 T
b1001001011000000000000000000 S
b11100 (
b11100 M
b11100 Q
b0 +
b0 >
b0 I
b100011 )
b100011 K
b10001110010010110000000000000000 *
b10001110010010110000000000000000 9
b10001110010010110000000000000000 A
b10001110010010110000000000000000 J
b10001110010010110000000000000000 P
b10001110010010110000000000000000 Y
b11100 R
b11000 '
b11000 H
b11000 N
b11000 O
1!
#840000
0!
#860000
b1010 $
b1010 F
b1010 X
b11 5
b11 <
b11 C
b11 D
b100000 (
b100000 M
b100000 Q
b100 T
b1001001100000000000000000100 S
b1 =
b100000 R
b1 +
b1 >
b1 I
b10001110010011000000000000000001 *
b10001110010011000000000000000001 9
b10001110010011000000000000000001 A
b10001110010011000000000000000001 J
b10001110010011000000000000000001 P
b10001110010011000000000000000001 Y
b11111111 %
b11111111 8
b11111111 E
b11111111 W
b11100 '
b11100 H
b11100 N
b11100 O
1!
#880000
0!
#900000
0U
0#
b1 5
b1 <
b1 C
b1 D
b1 $
b1 F
b1 X
b111 7
b111 ;
b111 @
b1010 &
b1010 :
b1010 V
b11111111 =
b10 6
b10 ?
b10 B
00
0.
04
1-
b11111111111111110000000010101000 T
b110001011110000000010101000 S
b100100 (
b100100 M
b100100 Q
b101010 +
b101010 >
b101010 I
b0 )
b0 K
b1100010111100000000101010 *
b1100010111100000000101010 9
b1100010111100000000101010 A
b1100010111100000000101010 J
b1100010111100000000101010 P
b1100010111100000000101010 Y
b100100 R
b100000 '
b100000 H
b100000 N
b100000 O
b11111111 %
b11111111 8
b11111111 E
b11111111 W
1!
#920000
0!
#940000
b0 =
b101000 (
b101000 M
b101000 Q
b110 7
b110 ;
b110 @
b1 &
b1 :
b1 V
b0 %
b0 8
b0 E
b0 W
b1000 T
b1100000000000000000000001000 S
b1 6
b1 ?
b1 B
12
0,
0-
b101000 R
b10 +
b10 >
b10 I
b100 )
b100 K
b10011000000000000000000000010 *
b10011000000000000000000000010 9
b10011000000000000000000000010 A
b10011000000000000000000000010 J
b10011000000000000000000000010 P
b10011000000000000000000000010 Y
b100100 '
b100100 H
b100100 N
b100100 O
1!
#960000
0!
